mdminify/__init__.py
mdminify/cli.py
mdminify/mdminify.py
mdminify/py.typed
mdminify-0.1.0.dist-info/METADATA
mdminify-0.1.0.dist-info/WHEEL
mdminify-0.1.0.dist-info/entry_points.txt
mdminify-0.1.0.dist-info/licenses/LICENSE
mdminify-0.1.0.dist-info/RECORD
